README.md
setup.py
emsa/__init__.py
emsa.egg-info/PKG-INFO
emsa.egg-info/SOURCES.txt
emsa.egg-info/dependency_links.txt
emsa.egg-info/requires.txt
emsa.egg-info/top_level.txt
emsa/generics/__init__.py
emsa/generics/generic_model.py
emsa/generics/generic_sampler.py
emsa/generics/simulation_generic.py
emsa/model/__init__.py
emsa/model/epidemic_model.py
emsa/model/matrix_generator.py
emsa/model/model_base.py
emsa/model/r0_calculator.py
emsa/sensitivity/__init__.py
emsa/sensitivity/prcc.py
emsa/sensitivity/sampler_base.py
emsa/sensitivity/sensitivity_model_base.py
emsa/sensitivity/target_calc/__init__.py
emsa/sensitivity/target_calc/output_generator.py
emsa/sensitivity/target_calc/r0_calculator_lhs.py
emsa/sensitivity/target_calc/sol_based_target_calc.py
emsa/utils/__init__.py
emsa/utils/dataloader.py
emsa/utils/plotter.py
emsa/utils/simulation_base.py
tests/test_examples.py
tests/test_solver.py