Metadata-Version: 2.2
Name: emsa
Version: 1.0.3
Summary: Efficient sensitivity analysis and evaluation of epidemiological models
Home-page: https://github.com/KKol21/epimodel_sensitivity
Author: Kolos Kovács
Author-email: kovkol21@gmail.com
Classifier: Programming Language :: Python :: 3
Classifier: Operating System :: OS Independent
Requires-Dist: torch~=2.3.0
Requires-Dist: torchode~=0.2.0
Requires-Dist: numpy~=1.26.4
Requires-Dist: matplotlib~=3.7.5
Requires-Dist: tqdm~=4.66.5
Requires-Dist: smt~=2.6.3
Dynamic: author
Dynamic: author-email
Dynamic: classifier
Dynamic: description
Dynamic: description-content-type
Dynamic: home-page
Dynamic: requires-dist
Dynamic: summary
